datafolder/__init__.py
datafolder/_resources.py
datafolder/_cli.py
datafolder-0.3.6.dist-info/top_level.txt
datafolder-0.3.6.dist-info/entry_points.txt
datafolder-0.3.6.dist-info/RECORD
datafolder-0.3.6.dist-info/WHEEL
datafolder-0.3.6.dist-info/METADATA
datafolder-0.3.6.dist-info/DESCRIPTION.rst
datafolder-0.3.6.dist-info/metadata.json
