Metadata-Version: 2.0
Name: datafolder
Version: 0.3.6
Summary: Install and access data files (conf, json, sqlite3, ...) in an easy way.
Home-page: https://github.com/xlcnd/datafolder
Author: xlcnd
Author-email: xlcnd@outlook.com
License: MIT
Keywords: packaging,setuptools,installation,discover,data files
Platform: UNKNOWN
Classifier: Programming Language :: Python
Classifier: Programming Language :: Python :: 2
Classifier: Programming Language :: Python :: 2.6
Classifier: Programming Language :: Python :: 2.7
Classifier: Programming Language :: Python :: 3
Classifier: Programming Language :: Python :: 3.1
Classifier: Programming Language :: Python :: 3.2
Classifier: Programming Language :: Python :: 3.3
Classifier: Programming Language :: Python :: 3.4
Classifier: License :: OSI Approved :: MIT License
Classifier: Operating System :: OS Independent
Classifier: Development Status :: 4 - Beta
Classifier: Intended Audience :: Developers
Classifier: Environment :: Console
Classifier: Topic :: System :: Installation/Setup
Classifier: Topic :: Software Development :: Libraries :: Python Modules
